{
    "name": "All Requests",
    "numberOfRequests": {
        "total": 61503,
        "ok": 61500,
        "ko": 3
    },
    "minResponseTime": {
        "total": 1,
        "ok": 1,
        "ko": 4
    },
    "maxResponseTime": {
        "total": 439,
        "ok": 439,
        "ko": 8
    },
    "meanResponseTime": {
        "total": 14,
        "ok": 14,
        "ko": 7
    },
    "standardDeviation": {
        "total": 14,
        "ok": 14,
        "ko": 2
    },
    "percentiles1": {
        "total": 7,
        "ok": 7,
        "ko": 8
    },
    "percentiles2": {
        "total": 17,
        "ok": 17,
        "ko": 8
    },
    "percentiles3": {
        "total": 41,
        "ok": 41,
        "ko": 8
    },
    "percentiles4": {
        "total": 55,
        "ok": 55,
        "ko": 8
    },
    "group1": {
    "name": "t < 250 ms",
    "htmlName": "t < 250 ms",
    "count": 61490,
    "percentage": 100
},
    "group2": {
    "name": "250 ms <= t < 1200 ms",
    "htmlName": "t >= 250 ms <br> t < 1200 ms",
    "count": 10,
    "percentage": 0
},
    "group3": {
    "name": "t >= 1200 ms",
    "htmlName": "t >= 1200 ms",
    "count": 0,
    "percentage": 0
},
    "group4": {
    "name": "failed",
    "htmlName": "failed",
    "count": 3,
    "percentage": 0
},
    "meanNumberOfRequestsPerSecond": {
        "total": 250.0121951219512,
        "ok": 250.0,
        "ko": 0.012195121951219513
    }
}