{
    "name": "All Requests",
    "numberOfRequests": {
        "total": 61483,
        "ok": 1892,
        "ko": 59591
    },
    "minResponseTime": {
        "total": 1,
        "ok": 1,
        "ko": 1
    },
    "maxResponseTime": {
        "total": 1890,
        "ok": 197,
        "ko": 1890
    },
    "meanResponseTime": {
        "total": 12,
        "ok": 8,
        "ko": 12
    },
    "standardDeviation": {
        "total": 42,
        "ok": 19,
        "ko": 42
    },
    "percentiles1": {
        "total": 3,
        "ok": 2,
        "ko": 3
    },
    "percentiles2": {
        "total": 5,
        "ok": 4,
        "ko": 5
    },
    "percentiles3": {
        "total": 63,
        "ok": 52,
        "ko": 64
    },
    "percentiles4": {
        "total": 93,
        "ok": 87,
        "ko": 93
    },
    "group1": {
    "name": "t < 250 ms",
    "htmlName": "t < 250 ms",
    "count": 1892,
    "percentage": 3
},
    "group2": {
    "name": "250 ms <= t < 1200 ms",
    "htmlName": "t >= 250 ms <br> t < 1200 ms",
    "count": 0,
    "percentage": 0
},
    "group3": {
    "name": "t >= 1200 ms",
    "htmlName": "t >= 1200 ms",
    "count": 0,
    "percentage": 0
},
    "group4": {
    "name": "failed",
    "htmlName": "failed",
    "count": 59591,
    "percentage": 97
},
    "meanNumberOfRequestsPerSecond": {
        "total": 249.9308943089431,
        "ok": 7.691056910569106,
        "ko": 242.239837398374
    }
}